LLIC/LLIC.py
LLIC/__init__.py
LLIC-0.1.13.dist-info/METADATA
LLIC-0.1.13.dist-info/WHEEL
LLIC-0.1.13.dist-info/top_level.txt
LLIC-0.1.13.dist-info/RECORD
