Metadata-Version: 2.1
Name: LLIC
Version: 0.1.13
Summary: Lightweight Learned Image Compression
Author-email: Dan Jacobellis <danjacobellis@utexas.edu>
Classifier: Programming Language :: Python :: 3
Classifier: Operating System :: OS Independent
Requires-Python: >=3.6
Requires-Dist: torch
Requires-Dist: compressai
Requires-Dist: numpy
